tttrlib/__init__.py
tttrlib/_tttrlib.pyd
tttrlib/tttrlib.py
tttrlib-0.24.4.dist-info/AUTHORS
tttrlib-0.24.4.dist-info/LICENSE.txt
tttrlib-0.24.4.dist-info/METADATA
tttrlib-0.24.4.dist-info/WHEEL
tttrlib-0.24.4.dist-info/top_level.txt
tttrlib-0.24.4.dist-info/RECORD
