Metadata-Version: 2.1
Name: tttrlib
Version: 0.24.4
Summary: Read, write & process time-tagged time-resolved (TTTR) data.
Author-email: author = Thomas-Otavio Peulen <thomas.otavio.peulen@gmail.com>
License: 
Project-URL: homepage, https://github.com/fluorescence-tools/tttrlib
Project-URL: documentation, https://docs.peulen.xyz/tttrlib
Project-URL: repository, https://github.com/fluorescence-tools/tttrlib.git
Keywords: fluorescence,time-resolved,spectroscopy,imaging,microscopy
Classifier: Topic :: Software Development
Classifier: Development Status :: 2 - Pre-Alpha
Classifier: Operating System :: POSIX :: Linux
Classifier: Operating System :: MacOS
Classifier: Operating System :: Microsoft :: Windows
Classifier: Intended Audience :: Education
Classifier: Intended Audience :: Developers
Classifier: Intended Audience :: Science/Research
Classifier: Topic :: Scientific/Engineering
Classifier: Topic :: Scientific/Engineering :: Physics
Classifier: Topic :: Scientific/Engineering :: Chemistry
Classifier: Topic :: Scientific/Engineering :: Bio-Informatics
Classifier: Topic :: Scientific/Engineering :: Image Processing
Classifier: Topic :: Software Development :: Libraries :: Python Modules
Classifier: License :: OSI Approved :: BSD License
Classifier: Programming Language :: C++
Classifier: Programming Language :: Python :: 3 :: Only
Requires-Python: >=3.8
License-File: LICENSE.txt
License-File: AUTHORS
Requires-Dist: numpy
